kubey/__init__.py
kubey/background_popen.py
kubey/cache.py
kubey/cli.py
kubey/condition.py
kubey/container.py
kubey/event.py
kubey/item.py
kubey/kubectl.py
kubey/kubey.py
kubey/node.py
kubey/openitem.py
kubey/pod.py
kubey/serializers.py
kubey/table_row_popen.py
kubey/tabular.py
kubey/timestamp.py
kubey-1.0.2.dist-info/DESCRIPTION.rst
kubey-1.0.2.dist-info/METADATA
kubey-1.0.2.dist-info/RECORD
kubey-1.0.2.dist-info/WHEEL
kubey-1.0.2.dist-info/entry_points.txt
kubey-1.0.2.dist-info/metadata.json
kubey-1.0.2.dist-info/top_level.txt
