Metadata-Version: 2.0
Name: kubey
Version: 1.0.2
Summary: Simple wrapper to help find specific Kubernetes pods and containers and run asynchronous commands.
Home-page: https://github.com/bradrf/kubey
Author: Brad Robel-Forrest
Author-email: brad@bitpony.com
License: MIT license
Keywords: kubey
Platform: UNKNOWN
Classifier: Development Status :: 2 - Pre-Alpha
Classifier: Intended Audience :: Developers
Classifier: License :: OSI Approved :: MIT License
Classifier: Natural Language :: English
Classifier: Programming Language :: Python :: 2
Classifier: Programming Language :: Python :: 2.7
Classifier: Programming Language :: Python :: 3
Classifier: Programming Language :: Python :: 3.3
Classifier: Programming Language :: Python :: 3.4
Classifier: Programming Language :: Python :: 3.5
Classifier: Programming Language :: Python :: 3.6
Requires-Dist: click (>=6.7)
Requires-Dist: configstruct (>=0.3.1)
Requires-Dist: python-dateutil (>=2.6.0)
Requires-Dist: tabulate (>=0.7.7)
